alu.v
module alu(
    input [31:0] a,
    input [31:0] b,
    input [2:0] aluctrl,
    output reg [31:0] result
);
always@(*) begin
case(aluctrl)
3'b000: result= a+b; // add
3'b001: result=a-b;//sub
3'b010: result=a&b;//and
3'b011: result=a|b;//or
3'b100: result= a<<b[4:0]; // SLL, shift left logical
3'b101: result= a>>b[4:0]; // SRL, shift right logical
3'b110: result= $signed(a) >>> b[4:0]; // SRA, shift right arithmetic
3'b111: result=a^b; //xor

default: result=0; // default case
endcase
end
endmodule

tb/alu_tb.v
module alu_tb;

reg  [31:0] a;
reg  [31:0] b;
reg  [2:0]  aluctrl;
wire [31:0] result;

alu dut(
    .a(a),
    .b(b),
    .aluctrl(aluctrl),
    .result(result)
);

initial begin
    $dumpfile("alu_tb.vcd");
    $dumpvars(0, alu_tb);

    $monitor("T=%0t ALUCTRL=%b A=%h B=%h RESULT=%h",
              $time, aluctrl, a, b, result);

    // ADD
    a = 32'd10;
    b = 32'd5;
    aluctrl = 3'b000;
    #10;

    // SUB
    aluctrl = 3'b001;
    #10;

    // AND
    a = 32'hF0F0F0F0;
    b = 32'h0F0F0F0F;
    aluctrl = 3'b010;
    #10;

    // OR
    aluctrl = 3'b011;
    #10;

    // SLL (4 << 2 = 16)
    a = 32'd4;
    b = 32'd2;
    aluctrl = 3'b100;
    #10;

    // SRL (16 >> 2 = 4)
    a = 32'd16;
    b = 32'd2;
    aluctrl = 3'b101;
    #10;

    // SRA (-16 >>> 2 = -4)
    a = -32'd16;
    b = 32'd2;
    aluctrl = 3'b110;
    #10;

    // XOR
    a = 32'hAA55AA55;
    b = 32'hFFFF0000;
    aluctrl = 3'b111;
    #10;

    $finish;
end

endmodule

alu_tb.vcd
$date
	Sat May 30 20:24:44 2026
$end
$version
	Icarus Verilog
$end
$timescale
	1s
$end
$scope module alu_tb $end
$var wire 32 ! result [31:0] $end
$var reg 32 " a [31:0] $end
$var reg 3 # aluctrl [2:0] $end
$var reg 32 $ b [31:0] $end
$scope module dut $end
$var wire 32 % a [31:0] $end
$var wire 3 & aluctrl [2:0] $end
$var wire 32 ' b [31:0] $end
$var reg 32 ( result [31:0] $end
$upscope $end
$upscope $end
$enddefinitions $end
$comment Show the parameter values. $end
$dumpall
$end
#0
$dumpvars
b1111 (
b101 '
b0 &
b1010 %
b101 $
b0 #
b1010 "
b1111 !
$end
#10
b101 !
b101 (
b1 #
b1 &
#20
b0 !
b0 (
b10 #
b10 &
b1111000011110000111100001111 $
b1111000011110000111100001111 '
b11110000111100001111000011110000 "
b11110000111100001111000011110000 %
#30
b11111111111111111111111111111111 !
b11111111111111111111111111111111 (
b11 #
b11 &
#40
b10000 !
b10000 (
b100 #
b100 &
b10 $
b10 '
b100 "
b100 %
#50
b100 !
b100 (
b101 #
b101 &
b10000 "
b10000 %
#60
b11111111111111111111111111111100 !
b11111111111111111111111111111100 (
b110 #
b110 &
b11111111111111111111111111110000 "
b11111111111111111111111111110000 %
#70
b1010101101010101010101001010101 !
b1010101101010101010101001010101 (
b111 #
b111 &
b11111111111111110000000000000000 $
b11111111111111110000000000000000 '
b10101010010101011010101001010101 "
b10101010010101011010101001010101 %
