rtl/result_mux.v
module result_mux(
    input [1:0] result_src,
    input [31:0] result, // Output from ALU 
    input [31:0] read_data, // Data read from memory
    input [31:0] pc_plus_4, // Next PC value
    output reg [31:0] mux_output
);

always @(*) begin
    case (result_src)
        2'b00: mux_output = result; // ALU result
        2'b01: mux_output = read_data; // Data from memory
        2'b10: mux_output = pc_plus_4; // Next PC value
        default: mux_output = 32'b0; // Default case
    endcase
end
endmodule

data_mem.v
module data_mem(
    input clk,
    input [31:0] addr,
    input [31:0] write_data, // RD2 from register file
    input memwrite,
    output reg [31:0] read_data );
reg [31:0] memory  [0:255]; 
always@(posedge clk) begin
    if(memwrite) begin
        memory[addr[7:0]]<=write_data; // Write data to memory at the specified address
    end
    
end
always@(*) begin
    read_data=memory[addr[7:0]]; // Output the data read from memory
end 
endmodule

mux_srcb.v
module mux_srcb(
    input [31:0] RD2,
    input  [31:0] imm_ext,
    input  alusrc,
    output reg  [31:0] srcb
);
always @(*) begin
    case (alusrc)
    1'b0: srcb=RD2; // R-type instructions use register data
    1'b1: srcb=imm_ext; // I-type instructions use immediate value

    default: srcb=32'b0; // Default case
    endcase
end
endmodule

extender.v
module extender(
    input signed [11:0] imm,
    input [1:0] immsrc,
    output reg signed [31:0] imm_ext

);

always @(*) begin
    case (immsrc)
        2'b00: imm_ext = {{20{imm[11]}}, imm}; // I-type
        2'b01: imm_ext = {{20{imm[11]}}, imm}; // S-type (same as I-type)
        2'b10: imm_ext = {{20{imm[11]}}, imm}; // B-type (same as I-type)
        default: imm_ext = 32'b0; // Default case
    endcase
end
endmodule

alu.v
module alu(
    input [31:0] a,
    input [31:0] b,
    input [2:0] aluctrl,
    output reg [31:0] result
);
always@(*) begin
case(aluctrl)
3'b000: result= a+b; // add
3'b001: result=a-b;//sub
3'b010: result=a&b;//and
3'b011: result=a|b;//or
3'b100: result= a<<b[4:0]; // SLL, shift left logical
3'b101: result= a>>b[4:0]; // SRL, shift right logical
3'b110: result= $signed(a) >>> b[4:0]; // SRA, shift right arithmetic
3'b111: result=a^b; //xor

default: result=0; // default case
endcase
end
endmodule

main_decoder.v
        //////// MAIN DECODER ////////
        module main_decoder(
        input [6:0] op,
        input memwrite,
        input [1:0] result_src,
        output reg [1:0] immsrc,
        output reg [1:0] aluop,
        
        output reg regwrite,
        output reg alusrc
        );
        always@(*) begin
        case(op)
        7'b0110011: begin // R-type
        aluop=2'b10; // ALU control determined by funct3 and funct7
        immsrc=2'b00; // No immediate
        regwrite=1; // Write to register
        alusrc=1'b0; // ALU source is 0 for R-type
        memwrite=0; // No memory write for R-type
        result_src=2'b00; // ALU result is written back to register
        end

        7'b0010011: begin // I-type
        aluop=2'b10; // ALU control determined by 
        immsrc=2'b00; // Immediate from instruction
        regwrite=1; // Write to register
        alusrc=1'b1; // ALU source is immediate for I-type
        memwrite=0; // No memory write for I-type
        result_src=2'b00; // ALU result is written back to register
        end
        7'b0000011: begin // Load
        aluop=2'b00; // ALU performs addition for address calculation
        immsrc=2'b00; // Immediate from instruction
        regwrite=1; // Write loaded value to register
        alusrc=1'b1; // ALU source is immediate for Load instructions
        memwrite=0; // No memory write for Load instructions
        result_src=2'b01; // Load result is written back to register
        end
    
        default: begin
            aluop   = 2'b00;
            immsrc  = 2'b00;
            regwrite= 1'b0;
            alusrc= 1'b0;
            memwrite=0;
            result_src=2'b00;
        end

        endcase
        end
        endmodule

        /////// ALU DECODER ///////////
        module alu_decoder(
            input [2:0] funct3,
            input [6:0] funct7,
            input [6:0] op,
            input [1:0] aluop,
            output reg [2:0] aluctrl
        );

        always @(*) begin
    case (aluop)
        2'b00: aluctrl = 3'b000; // add (loads/stores)
        2'b01: aluctrl = 3'b001; // sub (branches)
        default: begin
            case (funct3)
                3'b000:
                    aluctrl = (funct7 == 7'b0100000) ? 3'b001 : 3'b000; // sub/add
                3'b001: aluctrl = 3'b100; // SLL / SLLI
                3'b010:  aluctrl = 3'b001; // SLT / SLTI (signed compare)
					 3'b011:  aluctrl = 3'b010; // SLTU / SLTIU (unsigned compare)
                3'b100: aluctrl = 3'b111; // XOR / XORI
                3'b101: begin
                    aluctrl = (funct7 == 7'b0100000) ? 3'b110 : 3'b101;  // SRL/SRLI vs SRA/SRAI
                end
                3'b110: aluctrl = 3'b011; // OR / ORI
                3'b111: aluctrl = 3'b010; // AND / ANDI
                default: aluctrl = 3'b000;
            endcase
        end
    endcase
end


endmodule

register_file.v
module register_file(
    input clk,
    input [4:0] A1, // read register 1 
    input [4:0] A2, // read register 2 
    input [4:0] A3, // write register 
    input  WE3,      // write enable
    input [31:0] WD3, // write data
    output reg [31:0] RD1, // read data 1
    output reg [31:0] RD2  // read data 2
);
reg [31:0] registers [31:0]; // 32 registers, each 32 bits wide
always@(posedge clk) begin
    
        if(WE3) begin
        
        if(A3 != 0) begin// register x0 is always 0
        registers[A3] <= WD3; // write data to register
        end
         end

   

  end
  // read data from registers
always@(*) begin

        RD1 = (A1 == 5'd0) ? 32'h0 : registers[A1]; // read data from register rs1
        RD2 = (A2 == 5'd0) ? 32'h0 : registers[A2]; // read data from register rs2

    end
    initial begin
    // for testing: initialize registers
    registers[0]=32'h0; // x0 = 0
    registers[1]=32'h1; // x1 = 1
    registers[2]=32'h0; // x2 = 2
    registers[3]=32'h0; // x3 = 3
    registers[4]=32'h0; // x4 = 4
    end


endmodule

instr_memory.v
module instr_memory(
    input  [31:0] pc_addr,
    output [31:0] instr
);

    // Instruction memory (ROM)
    reg [31:0] mem [0:31];

    // Read instruction (combinational)
    assign instr = mem[pc_addr >> 2];

    // Initialize program
    initial begin
        $readmemh("itype_instr.hex",mem);
    end

endmodule

pc_inc.v
module pc_inc(
    input [31:0] pc,
    output [31:0] pc_plus_4
);
assign pc_plus_4 = pc + 4; // Increment PC by 4 for the next instruction
endmodule

rtl/pc.v
module pc(
    input clk,
    input reset,
    input [31:0] pc_next,
    output reg [31:0] pc
);

always @(posedge clk) begin
    if (reset)
        pc <= 32'b0;
    else
        pc <= pc_next;
end

endmodule

single_cycle_top.v
module single_cycle_top(
    input clk,
    input reset,
   
    
    output [31:0] pc, // testing
    output [31:0] instr, // testing

    output [6:0] op,
    output [2:0] funct3,
    output [6:0] funct7,
    output [4:0] rs1,
    output [4:0] rs2,
    output [4:0] rd,
    output WE3, //write enable for register file
    output [2:0] aluctrl,
    output [31:0] RD1,
    output [31:0] RD2,
    output [31:0] srcb, // output of mux_srcb
    output [31:0] read_data, // output from data memory
    output [31:0] pc_plus_4, // output from pc_inc
    output [1:0] result_src, // control signal for result_mux
    output [31:0] result,
    output [31:0] mux_output // output from result_mux, which is the data to write back to register file
);


wire memwrite; // control signal for memory write
wire regwrite; // control signal for register write
wire [31:0] pc_next;
wire [1:0] aluop;
wire [31:0] WD3; // write data for register file

wire [1:0] immsrc; // control signal for immediate source
wire alusrc; // control signal for ALU source
wire [31:0] imm_ext; // output from extender
wire [31:0] RD2; // output from register file

pc program_counter(
    .clk(clk),
    .reset(reset),
    .pc_next(pc_plus_4),
    .pc(pc)
);
pc_inc pc_incrementer(
    .pc(pc),
    .pc_plus_4(pc_plus_4)
);
instr_memory instr_mem(
    .pc_addr(pc), 
    .instr(instr)
);
register_file reg_file(
    .clk(clk),
    .A1(rs1),
    .A2(rs2),
    .A3(rd),
    .WE3(WE3),
    .WD3(mux_output), // Output from result_mux
    .RD1(RD1),
    .RD2(RD2)
);
main_decoder main_dec(
    .op(op),
    .regwrite(WE3),
    .immsrc(immsrc),
    .alusrc(alusrc),
    .aluop(aluop)
);
alu_decoder alu_dec(
    .op(op),
    .funct3(funct3),
    .funct7(funct7),
    .aluop(aluop),
    .aluctrl(aluctrl)
);

alu alu_unit(
    .a(RD1),
    .b(srcb), // Output from mux_srcb
    .aluctrl(aluctrl),
    .result(result)
);
extender  imm_extender_uut(
    .imm(instr[31:20]), // Immediate field for I-type instructions
    .immsrc(immsrc), // Control signal to select immediate type
    .imm_ext(imm_ext) // Output of the extender 
);
mux_srcb mux_srcb_unit(
    .RD2(RD2),
    .imm_ext(imm_ext), // Output from extender (not connected in this snippet)
    .alusrc(alusrc), // Control signal to select between RD2 and imm_ext 
    .srcb(srcb) // Output of the mux 
);
data_mem data_memory(
    .clk(clk),
    .addr(result), // Address for memory access (output from ALU)
    .write_data(RD2), // Data to write to memory (RD2 from register file)
    .memwrite(memwrite), // Control signal for memory write
    .read_data(read_data) // Data read from memory
);
result_mux write_back_mux(
    .result(result), // ALU result
    .read_data(read_data), // Data read from memory
    .pc_plus_4(pc_plus_4), // Next PC value
    .result_src(result_src), // Control signal to select between ALU result and memory data
    .mux_output(WD3) // Output of the mux, which is the data to write back to register file
);




assign op = instr[6:0];
assign funct3 = instr[14:12];
assign funct7 = instr[31:25];
assign rs1 = instr[19:15];
assign rs2 = instr[24:20];
assign rd = instr[11:7];
endmodule

pc_inst_tb.v
module pc_inst_tb;
reg clk;
reg reset;
wire [31:0] instr;
wire [31:0] pc; 

single_cycle_top uut (
    .clk(clk),
    .reset(reset),
    .pc(pc),
    .instr(instr)
);

initial begin 
    $dumpfile("pcinst.vcd");
    $dumpvars(0,pc_inst_tb);
end 
initial begin

$monitor("Time: %0t | PC: %h | Instr: %h", $time, pc, instr);   
end

initial begin
    clk=0; // Initialize clock
    forever #5 clk = ~clk; // Generate a clock signal with a period of 10 time units
end
initial begin 
    reset = 1;
    #10; // Wait for 10 time units
    reset = 0; // Release reset
    #100; // Wait for 100 time units to observe multiple instructions
    $finish; // End simulation
end
endmodule

pcinst.vcd
$date
	Thu May 28 13:32:13 2026
$end
$version
	Icarus Verilog
$end
$timescale
	1s
$end
$scope module pc_inst_tb $end
$var wire 32 ! pc [31:0] $end
$var wire 32 " instr [31:0] $end
$var reg 1 # clk $end
$var reg 1 $ reset $end
$scope module uut $end
$var wire 1 # clk $end
$var wire 1 $ reset $end
$var wire 5 % rs2 [4:0] $end
$var wire 5 & rs1 [4:0] $end
$var wire 5 ' rd [4:0] $end
$var wire 32 ( pc_next [31:0] $end
$var wire 32 ) pc [31:0] $end
$var wire 7 * op [6:0] $end
$var wire 32 + instr [31:0] $end
$var wire 7 , funct7 [6:0] $end
$var wire 3 - funct3 [2:0] $end
$scope module instr_mem $end
$var wire 32 . instr [31:0] $end
$var wire 32 / pc_addr [31:0] $end
$upscope $end
$scope module program_counter $end
$var wire 1 # clk $end
$var wire 32 0 pc_next [31:0] $end
$var wire 1 $ reset $end
$var reg 32 1 pc [31:0] $end
$upscope $end
$upscope $end
$upscope $end
$enddefinitions $end
$comment Show the parameter values. $end
$dumpall
$end
#0
$dumpvars
bx 1
bx 0
bx /
bx .
bx -
bx ,
bx +
bx *
bx )
bx (
bx '
bx &
bx %
1$
0#
bx "
bx !
$end
#5
b1 '
b1 %
b0 &
b0 ,
b0 -
b10011 *
b100000000000010010011 "
b100000000000010010011 +
b100000000000010010011 .
b100 (
b100 0
b0 !
b0 )
b0 /
b0 1
1#
#10
0#
0$
#15
b10 '
b10000 %
b1000000000000000100010011 "
b1000000000000000100010011 +
b1000000000000000100010011 .
b1000 (
b1000 0
b100 !
b100 )
b100 /
b100 1
1#
#20
0#
#25
b1110 '
b1 %
b10 &
b110011 *
b100010000011100110011 "
b100010000011100110011 +
b100010000011100110011 .
b1100 (
b1100 0
b1000 !
b1000 )
b1000 /
b1000 1
1#
#30
0#
#35
b1111 '
b100000 ,
b1000000000100010000011110110011 "
b1000000000100010000011110110011 +
b1000000000100010000011110110011 .
b10000 (
b10000 0
b1100 !
b1100 )
b1100 /
b1100 1
1#
#40
0#
#45
b10110 '
b0 ,
b110 -
b100010110101100110011 "
b100010110101100110011 +
b100010110101100110011 .
b10100 (
b10100 0
b10000 !
b10000 )
b10000 /
b10000 1
1#
#50
0#
#55
b10111 '
b111 -
b100010111101110110011 "
b100010111101110110011 +
b100010111101110110011 .
b11000 (
b11000 0
b10100 !
b10100 )
b10100 /
b10100 1
1#
#60
0#
#65
b0 '
b0 %
b0 &
b0 -
b10011 *
b10011 "
b10011 +
b10011 .
b11100 (
b11100 0
b11000 !
b11000 )
b11000 /
b11000 1
1#
#70
0#
#75
b100000 (
b100000 0
b11100 !
b11100 )
b11100 /
b11100 1
1#
#80
0#
#85
b100100 (
b100100 0
b100000 !
b100000 )
b100000 /
b100000 1
1#
#90
0#
#95
bx '
bx %
bx &
bx ,
bx -
bx *
bx "
bx +
bx .
b101000 (
b101000 0
b100100 !
b100100 )
b100100 /
b100100 1
1#
#100
0#
#105
b101100 (
b101100 0
b101000 !
b101000 )
b101000 /
b101000 1
1#
